[
  {
    "profile_id": 0,
    "agents": [
      {
        "agent_id": 0,
        "strategy": "MELO_0_100",
        "payoff": 17254.824971923827
      },
      {
        "agent_id": 1,
        "strategy": "MELO_0_100",
        "payoff": 14953.789885253906
      },
      {
        "agent_id": 2,
        "strategy": "MELO_0_100",
        "payoff": 24815.673702392578
      },
      {
        "agent_id": 3,
        "strategy": "MELO_0_100",
        "payoff": 28853.47849121094
      },
      {
        "agent_id": 4,
        "strategy": "MELO_0_100",
        "payoff": 26996.38101257324
      },
      {
        "agent_id": 5,
        "strategy": "MELO_0_100",
        "payoff": 29151.47183898926
      },
      {
        "agent_id": 6,
        "strategy": "MELO_0_100",
        "payoff": 28746.444256591796
      },
      {
        "agent_id": 7,
        "strategy": "MELO_0_100",
        "payoff": 27598.769913330078
      },
      {
        "agent_id": 8,
        "strategy": "MELO_100_0",
        "payoff": 32525.513482666014
      },
      {
        "agent_id": 9,
        "strategy": "MELO_100_0",
        "payoff": 30732.305998535157
      }
    ],
    "average_payoff": 26162.86535534668,
    "strategy_distribution": {
      "MELO_0_100": 8,
      "MELO_100_0": 2
    }
  },
  {
    "profile_id": 1,
    "agents": [
      {
        "agent_id": 0,
        "strategy": "MELO_0_100",
        "payoff": 20776.34848388672
      },
      {
        "agent_id": 1,
        "strategy": "MELO_100_0",
        "payoff": 27279.503076171874
      },
      {
        "agent_id": 2,
        "strategy": "MELO_100_0",
        "payoff": 24200.891362304686
      },
      {
        "agent_id": 3,
        "strategy": "MELO_100_0",
        "payoff": 22670.58794921875
      },
      {
        "agent_id": 4,
        "strategy": "MELO_100_0",
        "payoff": 22666.000913085936
      },
      {
        "agent_id": 5,
        "strategy": "MELO_100_0",
        "payoff": 25060.225053710936
      },
      {
        "agent_id": 6,
        "strategy": "MELO_100_0",
        "payoff": 21381.15671875
      },
      {
        "agent_id": 7,
        "strategy": "MELO_100_0",
        "payoff": 23736.047001953124
      },
      {
        "agent_id": 8,
        "strategy": "MELO_100_0",
        "payoff": 22957.376999511718
      },
      {
        "agent_id": 9,
        "strategy": "MELO_100_0",
        "payoff": 0.0
      }
    ],
    "average_payoff": 21072.813755859377,
    "strategy_distribution": {
      "MELO_0_100": 1,
      "MELO_100_0": 9
    }
  },
  {
    "profile_id": 2,
    "agents": [
      {
        "agent_id": 0,
        "strategy": "MELO_0_100",
        "payoff": 18159.116281738283
      },
      {
        "agent_id": 1,
        "strategy": "MELO_0_100",
        "payoff": 19447.508682861328
      },
      {
        "agent_id": 2,
        "strategy": "MELO_0_100",
        "payoff": 19512.6598046875
      },
      {
        "agent_id": 3,
        "strategy": "MELO_0_100",
        "payoff": 23800.515653686525
      },
      {
        "agent_id": 4,
        "strategy": "MELO_0_100",
        "payoff": 29789.276669921874
      },
      {
        "agent_id": 5,
        "strategy": "MELO_0_100",
        "payoff": 26781.520443115234
      },
      {
        "agent_id": 6,
        "strategy": "MELO_0_100",
        "payoff": 27941.131301269532
      },
      {
        "agent_id": 7,
        "strategy": "MELO_100_0",
        "payoff": 27468.711350097656
      },
      {
        "agent_id": 8,
        "strategy": "MELO_100_0",
        "payoff": 30977.516467285157
      },
      {
        "agent_id": 9,
        "strategy": "MELO_100_0",
        "payoff": 26534.090708007814
      }
    ],
    "average_payoff": 25041.204736267093,
    "strategy_distribution": {
      "MELO_0_100": 7,
      "MELO_100_0": 3
    }
  },
  {
    "profile_id": 3,
    "agents": [
      {
        "agent_id": 0,
        "strategy": "MELO_0_100",
        "payoff": 17614.12594116211
      },
      {
        "agent_id": 1,
        "strategy": "MELO_0_100",
        "payoff": 15969.612275390626
      },
      {
        "agent_id": 2,
        "strategy": "MELO_0_100",
        "payoff": 20550.29310058594
      },
      {
        "agent_id": 3,
        "strategy": "MELO_0_100",
        "payoff": 18970.83558959961
      },
      {
        "agent_id": 4,
        "strategy": "MELO_0_100",
        "payoff": 24609.51665283203
      },
      {
        "agent_id": 5,
        "strategy": "MELO_0_100",
        "payoff": 27806.24578979492
      },
      {
        "agent_id": 6,
        "strategy": "MELO_100_0",
        "payoff": 29158.270581054687
      },
      {
        "agent_id": 7,
        "strategy": "MELO_100_0",
        "payoff": 23222.325791625975
      },
      {
        "agent_id": 8,
        "strategy": "MELO_100_0",
        "payoff": 27036.250867919924
      },
      {
        "agent_id": 9,
        "strategy": "MELO_100_0",
        "payoff": 25402.382421264647
      }
    ],
    "average_payoff": 23033.985901123047,
    "strategy_distribution": {
      "MELO_0_100": 6,
      "MELO_100_0": 4
    }
  },
  {
    "profile_id": 4,
    "agents": [
      {
        "agent_id": 0,
        "strategy": "MELO_0_100",
        "payoff": 28047.728146972655
      },
      {
        "agent_id": 1,
        "strategy": "MELO_0_100",
        "payoff": 32186.472602539063
      },
      {
        "agent_id": 2,
        "strategy": "MELO_0_100",
        "payoff": 30172.801760253908
      },
      {
        "agent_id": 3,
        "strategy": "MELO_0_100",
        "payoff": 30309.284598388673
      },
      {
        "agent_id": 4,
        "strategy": "MELO_0_100",
        "payoff": 30175.174034118652
      },
      {
        "agent_id": 5,
        "strategy": "MELO_0_100",
        "payoff": 32129.761240234377
      },
      {
        "agent_id": 6,
        "strategy": "MELO_0_100",
        "payoff": 30699.67606262207
      },
      {
        "agent_id": 7,
        "strategy": "MELO_0_100",
        "payoff": 31111.988815917968
      },
      {
        "agent_id": 8,
        "strategy": "MELO_0_100",
        "payoff": 31028.943681640623
      },
      {
        "agent_id": 9,
        "strategy": "MELO_0_100",
        "payoff": 31155.410230712892
      }
    ],
    "average_payoff": 30701.72411734009,
    "strategy_distribution": {
      "MELO_0_100": 10
    }
  },
  {
    "profile_id": 5,
    "agents": [
      {
        "agent_id": 0,
        "strategy": "MELO_100_0",
        "payoff": 22254.058857421875
      },
      {
        "agent_id": 1,
        "strategy": "MELO_100_0",
        "payoff": 25943.9800390625
      },
      {
        "agent_id": 2,
        "strategy": "MELO_100_0",
        "payoff": 22656.13914428711
      },
      {
        "agent_id": 3,
        "strategy": "MELO_100_0",
        "payoff": 21225.046975097655
      },
      {
        "agent_id": 4,
        "strategy": "MELO_100_0",
        "payoff": 25676.367258300783
      },
      {
        "agent_id": 5,
        "strategy": "MELO_100_0",
        "payoff": 27106.296916503907
      },
      {
        "agent_id": 6,
        "strategy": "MELO_100_0",
        "payoff": 25201.837678222655
      },
      {
        "agent_id": 7,
        "strategy": "MELO_100_0",
        "payoff": 23501.65532196045
      },
      {
        "agent_id": 8,
        "strategy": "MELO_100_0",
        "payoff": 23799.453317871095
      },
      {
        "agent_id": 9,
        "strategy": "MELO_100_0",
        "payoff": 22683.629345703124
      }
    ],
    "average_payoff": 24004.846485443115,
    "strategy_distribution": {
      "MELO_100_0": 10
    }
  },
  {
    "profile_id": 6,
    "agents": [
      {
        "agent_id": 0,
        "strategy": "MELO_0_100",
        "payoff": 20336.73995361328
      },
      {
        "agent_id": 1,
        "strategy": "MELO_0_100",
        "payoff": 16560.67037902832
      },
      {
        "agent_id": 2,
        "strategy": "MELO_0_100",
        "payoff": 20884.90833496094
      },
      {
        "agent_id": 3,
        "strategy": "MELO_0_100",
        "payoff": 19385.357896118163
      },
      {
        "agent_id": 4,
        "strategy": "MELO_0_100",
        "payoff": 16825.429609375
      },
      {
        "agent_id": 5,
        "strategy": "MELO_100_0",
        "payoff": 25167.750725708007
      },
      {
        "agent_id": 6,
        "strategy": "MELO_100_0",
        "payoff": 25789.964064941407
      },
      {
        "agent_id": 7,
        "strategy": "MELO_100_0",
        "payoff": 28565.716531677244
      },
      {
        "agent_id": 8,
        "strategy": "MELO_100_0",
        "payoff": 25832.86520980835
      },
      {
        "agent_id": 9,
        "strategy": "MELO_100_0",
        "payoff": 24983.150283203126
      }
    ],
    "average_payoff": 22433.255298843385,
    "strategy_distribution": {
      "MELO_0_100": 5,
      "MELO_100_0": 5
    }
  },
  {
    "profile_id": 7,
    "agents": [
      {
        "agent_id": 0,
        "strategy": "MELO_0_100",
        "payoff": 20359.721801757812
      },
      {
        "agent_id": 1,
        "strategy": "MELO_0_100",
        "payoff": 22002.307744140624
      },
      {
        "agent_id": 2,
        "strategy": "MELO_100_0",
        "payoff": 23450.37971435547
      },
      {
        "agent_id": 3,
        "strategy": "MELO_100_0",
        "payoff": 22621.05352294922
      },
      {
        "agent_id": 4,
        "strategy": "MELO_100_0",
        "payoff": 19763.426572265624
      },
      {
        "agent_id": 5,
        "strategy": "MELO_100_0",
        "payoff": 22269.002521972656
      },
      {
        "agent_id": 6,
        "strategy": "MELO_100_0",
        "payoff": 25014.880368652342
      },
      {
        "agent_id": 7,
        "strategy": "MELO_100_0",
        "payoff": 21347.666638183593
      },
      {
        "agent_id": 8,
        "strategy": "MELO_100_0",
        "payoff": 12393.949353637696
      },
      {
        "agent_id": 9,
        "strategy": "MELO_100_0",
        "payoff": 13373.76292541504
      }
    ],
    "average_payoff": 20259.61511633301,
    "strategy_distribution": {
      "MELO_0_100": 2,
      "MELO_100_0": 8
    }
  },
  {
    "profile_id": 8,
    "agents": [
      {
        "agent_id": 0,
        "strategy": "MELO_0_100",
        "payoff": 15416.515805664063
      },
      {
        "agent_id": 1,
        "strategy": "MELO_0_100",
        "payoff": 31396.462451171876
      },
      {
        "agent_id": 2,
        "strategy": "MELO_0_100",
        "payoff": 30961.61421875
      },
      {
        "agent_id": 3,
        "strategy": "MELO_0_100",
        "payoff": 31008.35857421875
      },
      {
        "agent_id": 4,
        "strategy": "MELO_0_100",
        "payoff": 29913.113387451172
      },
      {
        "agent_id": 5,
        "strategy": "MELO_0_100",
        "payoff": 30309.390205078125
      },
      {
        "agent_id": 6,
        "strategy": "MELO_0_100",
        "payoff": 30907.859928588867
      },
      {
        "agent_id": 7,
        "strategy": "MELO_0_100",
        "payoff": 30449.36531890869
      },
      {
        "agent_id": 8,
        "strategy": "MELO_0_100",
        "payoff": 30578.042690429687
      },
      {
        "agent_id": 9,
        "strategy": "MELO_100_0",
        "payoff": 30252.661983642578
      }
    ],
    "average_payoff": 29119.33845639038,
    "strategy_distribution": {
      "MELO_0_100": 9,
      "MELO_100_0": 1
    }
  },
  {
    "profile_id": 9,
    "agents": [
      {
        "agent_id": 0,
        "strategy": "MELO_0_100",
        "payoff": 19833.581304931642
      },
      {
        "agent_id": 1,
        "strategy": "MELO_0_100",
        "payoff": 22190.718742980956
      },
      {
        "agent_id": 2,
        "strategy": "MELO_0_100",
        "payoff": 20492.165307617186
      },
      {
        "agent_id": 3,
        "strategy": "MELO_100_0",
        "payoff": 21065.447870025633
      },
      {
        "agent_id": 4,
        "strategy": "MELO_100_0",
        "payoff": 20635.710510253906
      },
      {
        "agent_id": 5,
        "strategy": "MELO_100_0",
        "payoff": 20528.606350097656
      },
      {
        "agent_id": 6,
        "strategy": "MELO_100_0",
        "payoff": 21227.48748901367
      },
      {
        "agent_id": 7,
        "strategy": "MELO_100_0",
        "payoff": 20312.413494873046
      },
      {
        "agent_id": 8,
        "strategy": "MELO_100_0",
        "payoff": 23903.14694946289
      },
      {
        "agent_id": 9,
        "strategy": "MELO_100_0",
        "payoff": 19528.808732299804
      }
    ],
    "average_payoff": 20971.80867515564,
    "strategy_distribution": {
      "MELO_0_100": 3,
      "MELO_100_0": 7
    }
  },
  {
    "profile_id": 10,
    "agents": [
      {
        "agent_id": 0,
        "strategy": "MELO_0_100",
        "payoff": 19283.271754760743
      },
      {
        "agent_id": 1,
        "strategy": "MELO_0_100",
        "payoff": 21284.43815917969
      },
      {
        "agent_id": 2,
        "strategy": "MELO_0_100",
        "payoff": 19730.519169921874
      },
      {
        "agent_id": 3,
        "strategy": "MELO_0_100",
        "payoff": 23650.731508789064
      },
      {
        "agent_id": 4,
        "strategy": "MELO_100_0",
        "payoff": 22334.496987304687
      },
      {
        "agent_id": 5,
        "strategy": "MELO_100_0",
        "payoff": 18002.383770751952
      },
      {
        "agent_id": 6,
        "strategy": "MELO_100_0",
        "payoff": 25447.09990539551
      },
      {
        "agent_id": 7,
        "strategy": "MELO_100_0",
        "payoff": 25456.666640625
      },
      {
        "agent_id": 8,
        "strategy": "MELO_100_0",
        "payoff": 25066.299528808595
      },
      {
        "agent_id": 9,
        "strategy": "MELO_100_0",
        "payoff": 26712.076880493165
      }
    ],
    "average_payoff": 22696.798430603027,
    "strategy_distribution": {
      "MELO_0_100": 4,
      "MELO_100_0": 6
    }
  }
]